{
    "id": "4501f59c-1816-4837-8214-2aa5d8237166",
    "status": "completed",
    "trigger_type": "manual",
    "total_keywords": 58,
    "high_opportunity_count": 0,
    "keywords": [
        {
            "cpc": 0,
            "intent": "Informational",
            "source": "google_autocomplete",
            "keyword": "explain how search engines work",
            "placement": "Title_H1",
            "difficulty": 50,
            "competition": 0.5,
            "seed_keyword": "how search engines work",
            "is_hidden_gem": true,
            "search_volume": 0,
            "relevance_score": 0.5,
            "is_conversational": true,
            "opportunity_score": 43,
            "ai_authority_score": 85,
            "ai_visibility_score": 5.0
        },
        {
            "cpc": 0,
            "intent": "Informational",
            "source": "google_autocomplete",
            "keyword": "how search engines work for kids",
            "placement": "Section_H2",
            "difficulty": 50,
            "competition": 0.5,
            "seed_keyword": "how search engines work",
            "is_hidden_gem": true,
            "search_volume": 0,
            "relevance_score": 0.5,
            "is_conversational": true,
            "opportunity_score": 38,
            "ai_authority_score": 75,
            "ai_visibility_score": 8.0
        },
        {
            "cpc": 0,
            "intent": "Informational",
            "source": "google_autocomplete",
            "keyword": "how search engines operate",
            "placement": "Section_H2",
            "difficulty": 50,
            "competition": 0.5,
            "seed_keyword": "how search engines work",
            "is_hidden_gem": false,
            "search_volume": 0,
            "relevance_score": 0.5,
            "is_conversational": false,
            "opportunity_score": 0,
            "ai_authority_score": 60,
            "ai_visibility_score": 7.0
        },
        {
            "cpc": 0,
            "intent": "Informational",
            "source": "google_autocomplete",
            "keyword": "how search engines work video",
            "placement": "Body_Content",
            "difficulty": 50,
            "competition": 0.5,
            "seed_keyword": "how search engines work",
            "is_hidden_gem": false,
            "search_volume": 0,
            "relevance_score": 0.5,
            "is_conversational": false,
            "opportunity_score": 0,
            "ai_authority_score": 50,
            "ai_visibility_score": 8.0
        },
        {
            "cpc": 0,
            "intent": "Navigational",
            "source": "google_autocomplete",
            "keyword": "how search engines work bbc bitesize",
            "placement": "Body_Content",
            "difficulty": 50,
            "competition": 0.5,
            "seed_keyword": "how search engines work",
            "is_hidden_gem": false,
            "search_volume": 0,
            "relevance_score": 0.5,
            "is_conversational": false,
            "opportunity_score": 0,
            "ai_authority_score": 50,
            "ai_visibility_score": 8.0
        },
        {
            "cpc": 0,
            "intent": "Informational",
            "source": "google_autocomplete",
            "keyword": "how search engines work ks2",
            "placement": "Body_Content",
            "difficulty": 50,
            "competition": 0.5,
            "seed_keyword": "how search engines work",
            "is_hidden_gem": false,
            "search_volume": 0,
            "relevance_score": 0.5,
            "is_conversational": false,
            "opportunity_score": 0,
            "ai_authority_score": 50,
            "ai_visibility_score": 8.0
        },
        {
            "cpc": 0,
            "intent": "Informational",
            "source": "google_autocomplete",
            "keyword": "how search engines work understanding google and bing",
            "placement": "Section_H2",
            "difficulty": 50,
            "competition": 0.5,
            "seed_keyword": "how search engines work",
            "is_hidden_gem": false,
            "search_volume": 0,
            "relevance_score": 0.5,
            "is_conversational": false,
            "opportunity_score": 0,
            "ai_authority_score": 60,
            "ai_visibility_score": 8.0
        },
        {
            "cpc": 0,
            "intent": "Informational",
            "source": "google_autocomplete",
            "keyword": "how search engines work pdf",
            "placement": "Body_Content",
            "difficulty": 50,
            "competition": 0.5,
            "seed_keyword": "how search engines work",
            "is_hidden_gem": false,
            "search_volume": 0,
            "relevance_score": 0.5,
            "is_conversational": false,
            "opportunity_score": 0,
            "ai_authority_score": 50,
            "ai_visibility_score": 8.0
        },
        {
            "cpc": 0,
            "source": "google_autocomplete",
            "keyword": "how search engines work crawling indexing and ranking",
            "difficulty": 50,
            "competition": 0.5,
            "seed_keyword": "how search engines work",
            "is_hidden_gem": false,
            "search_volume": 0,
            "relevance_score": 0.5,
            "opportunity_score": 0,
            "ai_visibility_score": 8.0
        },
        {
            "cpc": 0,
            "source": "google_autocomplete",
            "keyword": "how search engines work diagram",
            "difficulty": 50,
            "competition": 0.5,
            "seed_keyword": "how search engines work",
            "is_hidden_gem": false,
            "search_volume": 0,
            "relevance_score": 0.5,
            "opportunity_score": 0,
            "ai_visibility_score": 8.0
        },
        {
            "cpc": 0,
            "source": "google_autocomplete",
            "keyword": "bing search indexing",
            "difficulty": 50,
            "competition": 0.5,
            "seed_keyword": "Bing indexing",
            "is_hidden_gem": false,
            "search_volume": 0,
            "relevance_score": 0.5,
            "opportunity_score": 0,
            "ai_visibility_score": 4.0
        },
        {
            "cpc": 0,
            "source": "google_autocomplete",
            "keyword": "bing request indexing",
            "difficulty": 50,
            "competition": 0.5,
            "seed_keyword": "Bing indexing",
            "is_hidden_gem": false,
            "search_volume": 0,
            "relevance_score": 0.5,
            "opportunity_score": 0,
            "ai_visibility_score": 4.0
        },
        {
            "cpc": 0,
            "source": "google_autocomplete",
            "keyword": "bing instant indexing",
            "difficulty": 50,
            "competition": 0.5,
            "seed_keyword": "Bing indexing",
            "is_hidden_gem": false,
            "search_volume": 0,
            "relevance_score": 0.5,
            "opportunity_score": 0,
            "ai_visibility_score": 4.0
        },
        {
            "cpc": 0,
            "source": "google_autocomplete",
            "keyword": "bing website indexing",
            "difficulty": 50,
            "competition": 0.5,
            "seed_keyword": "Bing indexing",
            "is_hidden_gem": false,
            "search_volume": 0,
            "relevance_score": 0.5,
            "opportunity_score": 0,
            "ai_visibility_score": 4.0
        },
        {
            "cpc": 0,
            "source": "google_autocomplete",
            "keyword": "bing not indexing my site",
            "difficulty": 50,
            "competition": 0.5,
            "seed_keyword": "Bing indexing",
            "is_hidden_gem": false,
            "search_volume": 0,
            "relevance_score": 0.5,
            "opportunity_score": 0,
            "ai_visibility_score": 5.0
        },
        {
            "cpc": 0,
            "source": "google_autocomplete",
            "keyword": "bing indexing checker",
            "difficulty": 50,
            "competition": 0.5,
            "seed_keyword": "Bing indexing",
            "is_hidden_gem": false,
            "search_volume": 0,
            "relevance_score": 0.5,
            "opportunity_score": 0,
            "ai_visibility_score": 4.0
        },
        {
            "cpc": 0,
            "source": "google_autocomplete",
            "keyword": "bing indexing api key",
            "difficulty": 50,
            "competition": 0.5,
            "seed_keyword": "Bing indexing",
            "is_hidden_gem": false,
            "search_volume": 0,
            "relevance_score": 0.5,
            "opportunity_score": 0,
            "ai_visibility_score": 4.0
        },
        {
            "cpc": 0,
            "source": "google_autocomplete",
            "keyword": "bing indexing api",
            "difficulty": 50,
            "competition": 0.5,
            "seed_keyword": "Bing indexing",
            "is_hidden_gem": false,
            "search_volume": 0,
            "relevance_score": 0.5,
            "opportunity_score": 0,
            "ai_visibility_score": 4.0
        },
        {
            "cpc": 0,
            "source": "google_autocomplete",
            "keyword": "bing indexing tool",
            "difficulty": 50,
            "competition": 0.5,
            "seed_keyword": "Bing indexing",
            "is_hidden_gem": false,
            "search_volume": 0,
            "relevance_score": 0.5,
            "opportunity_score": 0,
            "ai_visibility_score": 4.0
        },
        {
            "cpc": 0,
            "source": "google_autocomplete",
            "keyword": "google seo keywords",
            "difficulty": 50,
            "competition": 0.5,
            "seed_keyword": "Google SEO",
            "is_hidden_gem": false,
            "search_volume": 0,
            "relevance_score": 0.5,
            "opportunity_score": 0,
            "ai_visibility_score": 4.0
        },
        {
            "cpc": 0,
            "source": "google_autocomplete",
            "keyword": "google seo starter guide",
            "difficulty": 50,
            "competition": 0.5,
            "seed_keyword": "Google SEO",
            "is_hidden_gem": false,
            "search_volume": 0,
            "relevance_score": 0.5,
            "opportunity_score": 0,
            "ai_visibility_score": 6.0
        },
        {
            "cpc": 0,
            "source": "google_autocomplete",
            "keyword": "google seo certification",
            "difficulty": 50,
            "competition": 0.5,
            "seed_keyword": "Google SEO",
            "is_hidden_gem": false,
            "search_volume": 0,
            "relevance_score": 0.5,
            "opportunity_score": 0,
            "ai_visibility_score": 4.0
        },
        {
            "cpc": 0,
            "source": "google_autocomplete",
            "keyword": "google seo updates",
            "difficulty": 50,
            "competition": 0.5,
            "seed_keyword": "Google SEO",
            "is_hidden_gem": false,
            "search_volume": 0,
            "relevance_score": 0.5,
            "opportunity_score": 0,
            "ai_visibility_score": 4.0
        },
        {
            "cpc": 0,
            "source": "google_autocomplete",
            "keyword": "google seo course free with certificate",
            "difficulty": 50,
            "competition": 0.5,
            "seed_keyword": "Google SEO",
            "is_hidden_gem": false,
            "search_volume": 0,
            "relevance_score": 0.5,
            "opportunity_score": 0,
            "ai_visibility_score": 5.0
        },
        {
            "cpc": 0,
            "source": "google_autocomplete",
            "keyword": "google seo meaning",
            "difficulty": 50,
            "competition": 0.5,
            "seed_keyword": "Google SEO",
            "is_hidden_gem": false,
            "search_volume": 0,
            "relevance_score": 0.5,
            "opportunity_score": 0,
            "ai_visibility_score": 4.0
        },
        {
            "cpc": 0,
            "source": "google_autocomplete",
            "keyword": "google seo checker",
            "difficulty": 50,
            "competition": 0.5,
            "seed_keyword": "Google SEO",
            "is_hidden_gem": false,
            "search_volume": 0,
            "relevance_score": 0.5,
            "opportunity_score": 0,
            "ai_visibility_score": 4.0
        },
        {
            "cpc": 0,
            "source": "google_autocomplete",
            "keyword": "google seo tools",
            "difficulty": 50,
            "competition": 0.5,
            "seed_keyword": "Google SEO",
            "is_hidden_gem": false,
            "search_volume": 0,
            "relevance_score": 0.5,
            "opportunity_score": 0,
            "ai_visibility_score": 4.0
        },
        {
            "cpc": 0,
            "source": "google_autocomplete",
            "keyword": "google seo course",
            "difficulty": 50,
            "competition": 0.5,
            "seed_keyword": "Google SEO",
            "is_hidden_gem": false,
            "search_volume": 0,
            "relevance_score": 0.5,
            "opportunity_score": 0,
            "ai_visibility_score": 4.0
        },
        {
            "cpc": 0,
            "source": "ai_prediction",
            "keyword": "how to ping Google",
            "difficulty": 50,
            "competition": 0.5,
            "is_hidden_gem": false,
            "search_volume": 0,
            "relevance_score": 0.6,
            "opportunity_score": 0,
            "ai_visibility_score": 5.0
        },
        {
            "cpc": 0,
            "source": "ai_prediction",
            "keyword": "Bing crawling guidelines",
            "difficulty": 50,
            "competition": 0.5,
            "is_hidden_gem": false,
            "search_volume": 0,
            "relevance_score": 0.6,
            "opportunity_score": 0,
            "ai_visibility_score": 5.0
        },
        {
            "cpc": 0,
            "source": "ai_prediction",
            "keyword": "SEO tips for Google",
            "difficulty": 50,
            "competition": 0.5,
            "is_hidden_gem": false,
            "search_volume": 0,
            "relevance_score": 0.6,
            "opportunity_score": 0,
            "ai_visibility_score": 5.0
        },
        {
            "cpc": 0,
            "source": "ai_prediction",
            "keyword": "how to optimize articles",
            "difficulty": 50,
            "competition": 0.5,
            "is_hidden_gem": false,
            "search_volume": 0,
            "relevance_score": 0.6,
            "opportunity_score": 0,
            "ai_visibility_score": 5.0
        },
        {
            "cpc": 0,
            "source": "ai_prediction",
            "keyword": "search engine API integration",
            "difficulty": 50,
            "competition": 0.5,
            "is_hidden_gem": false,
            "search_volume": 0,
            "relevance_score": 0.6,
            "opportunity_score": 0,
            "ai_visibility_score": 5.0
        },
        {
            "cpc": 0,
            "source": "ai_prediction",
            "keyword": "IndexNow for SEO",
            "difficulty": 50,
            "competition": 0.5,
            "is_hidden_gem": false,
            "search_volume": 0,
            "relevance_score": 0.6,
            "opportunity_score": 0,
            "ai_visibility_score": 5.0
        },
        {
            "cpc": 0,
            "source": "ai_prediction",
            "keyword": "how to use Googlebot",
            "difficulty": 50,
            "competition": 0.5,
            "is_hidden_gem": false,
            "search_volume": 0,
            "relevance_score": 0.6,
            "opportunity_score": 0,
            "ai_visibility_score": 5.0
        },
        {
            "cpc": 0,
            "source": "ai_prediction",
            "keyword": "Bing search engine ranking",
            "difficulty": 50,
            "competition": 0.5,
            "is_hidden_gem": false,
            "search_volume": 0,
            "relevance_score": 0.6,
            "opportunity_score": 0,
            "ai_visibility_score": 5.0
        },
        {
            "cpc": 0,
            "source": "ai_prediction",
            "keyword": "Google indexing issues",
            "difficulty": 50,
            "competition": 0.5,
            "is_hidden_gem": false,
            "search_volume": 0,
            "relevance_score": 0.6,
            "opportunity_score": 0,
            "ai_visibility_score": 5.0
        },
        {
            "cpc": 0,
            "source": "ai_prediction",
            "keyword": "SEO for publishers",
            "difficulty": 50,
            "competition": 0.5,
            "is_hidden_gem": false,
            "search_volume": 0,
            "relevance_score": 0.6,
            "opportunity_score": 0,
            "ai_visibility_score": 5.0
        },
        {
            "cpc": 0,
            "source": "ai_prediction",
            "keyword": "what is IndexNow API",
            "difficulty": 50,
            "competition": 0.5,
            "is_hidden_gem": false,
            "search_volume": 0,
            "relevance_score": 0.6,
            "opportunity_score": 0,
            "ai_visibility_score": 5.0
        },
        {
            "cpc": 0,
            "source": "ai_prediction",
            "keyword": "open-source publishing platforms",
            "difficulty": 50,
            "competition": 0.5,
            "is_hidden_gem": false,
            "search_volume": 0,
            "relevance_score": 0.6,
            "opportunity_score": 0,
            "ai_visibility_score": 5.0
        },
        {
            "cpc": 0,
            "source": "ai_prediction",
            "keyword": "how to improve website indexing",
            "difficulty": 50,
            "competition": 0.5,
            "is_hidden_gem": false,
            "search_volume": 0,
            "relevance_score": 0.6,
            "opportunity_score": 0,
            "ai_visibility_score": 5.0
        },
        {
            "cpc": 0,
            "source": "ai_prediction",
            "keyword": "API for article publishing",
            "difficulty": 50,
            "competition": 0.5,
            "is_hidden_gem": false,
            "search_volume": 0,
            "relevance_score": 0.6,
            "opportunity_score": 0,
            "ai_visibility_score": 5.0
        },
        {
            "cpc": 0,
            "source": "ai_prediction",
            "keyword": "search engine optimization guide",
            "difficulty": 50,
            "competition": 0.5,
            "is_hidden_gem": false,
            "search_volume": 0,
            "relevance_score": 0.6,
            "opportunity_score": 0,
            "ai_visibility_score": 5.0
        },
        {
            "cpc": 0,
            "source": "ai_prediction",
            "keyword": "how to use IndexNow",
            "difficulty": 50,
            "competition": 0.5,
            "is_hidden_gem": false,
            "search_volume": 0,
            "relevance_score": 0.6,
            "opportunity_score": 0,
            "ai_visibility_score": 5.0
        },
        {
            "cpc": 0,
            "source": "ai_prediction",
            "keyword": "Bing vs Google SEO",
            "difficulty": 50,
            "competition": 0.5,
            "is_hidden_gem": false,
            "search_volume": 0,
            "relevance_score": 0.6,
            "opportunity_score": 0,
            "ai_visibility_score": 5.0
        },
        {
            "cpc": 0,
            "source": "ai_prediction",
            "keyword": "best SEO practices 2023",
            "difficulty": 50,
            "competition": 0.5,
            "is_hidden_gem": false,
            "search_volume": 0,
            "relevance_score": 0.6,
            "opportunity_score": 0,
            "ai_visibility_score": 5.0
        },
        {
            "cpc": 0,
            "source": "ai_prediction",
            "keyword": "search engine publishing",
            "difficulty": 50,
            "competition": 0.5,
            "is_hidden_gem": false,
            "search_volume": 0,
            "relevance_score": 0.6,
            "opportunity_score": 0,
            "ai_visibility_score": 5.0
        },
        {
            "cpc": 0,
            "source": "ai_prediction",
            "keyword": "how to ping search engines",
            "difficulty": 50,
            "competition": 0.5,
            "is_hidden_gem": false,
            "search_volume": 0,
            "relevance_score": 0.6,
            "opportunity_score": 0,
            "ai_visibility_score": 5.0
        },
        {
            "cpc": 0,
            "source": "ai_prediction",
            "keyword": "IndexNow benefits",
            "difficulty": 50,
            "is_hidden_gem": false,
            "search_volume": 0,
            "relevance_score": 0.6,
            "opportunity_score": 0,
            "ai_visibility_score": 5.0
        },
        {
            "cpc": 0,
            "source": "ai_prediction",
            "keyword": "Googlebot crawling tips",
            "difficulty": 50,
            "competition": 0.5,
            "is_hidden_gem": false,
            "search_volume": 0,
            "relevance_score": 0.6,
            "opportunity_score": 0,
            "ai_visibility_score": 5.0
        },
        {
            "cpc": 0,
            "source": "ai_prediction",
            "keyword": "open-source SEO tools",
            "difficulty": 50,
            "competition": 0.5,
            "is_hidden_gem": false,
            "search_volume": 0,
            "relevance_score": 0.6,
            "opportunity_score": 0,
            "ai_visibility_score": 5.0
        },
        {
            "cpc": 0,
            "source": "ai_prediction",
            "keyword": "publish articles online",
            "difficulty": 50,
            "competition": 0.5,
            "is_hidden_gem": false,
            "search_volume": 0,
            "relevance_score": 0.6,
            "opportunity_score": 0,
            "ai_visibility_score": 5.0
        },
        {
            "cpc": 0,
            "source": "ai_prediction",
            "keyword": "API for search engines",
            "difficulty": 50,
            "competition": 0.5,
            "is_hidden_gem": false,
            "search_volume": 0,
            "relevance_score": 0.6,
            "opportunity_score": 0,
            "ai_visibility_score": 5.0
        },
        {
            "cpc": 0,
            "source": "ai_prediction",
            "keyword": "optimize for Googlebot",
            "difficulty": 50,
            "competition": 0.5,
            "is_hidden_gem": false,
            "search_volume": 0,
            "relevance_score": 0.6,
            "opportunity_score": 0,
            "ai_visibility_score": 5.0
        },
        {
            "cpc": 0,
            "source": "ai_prediction",
            "keyword": "how search engines work",
            "difficulty": 50,
            "competition": 0.5,
            "is_hidden_gem": false,
            "search_volume": 0,
            "relevance_score": 0.6,
            "opportunity_score": 0,
            "ai_visibility_score": 5.0
        },
        {
            "cpc": 0,
            "source": "ai_prediction",
            "keyword": "IndexNow API guide",
            "difficulty": 50,
            "competition": 0.5,
            "is_hidden_gem": false,
            "search_volume": 0,
            "relevance_score": 0.6,
            "opportunity_score": 0,
            "ai_visibility_score": 5.0
        },
        {
            "cpc": 0,
            "source": "ai_prediction",
            "keyword": "Bing indexing",
            "difficulty": 50,
            "competition": 0.5,
            "is_hidden_gem": false,
            "search_volume": 0,
            "relevance_score": 0.6,
            "opportunity_score": 0,
            "ai_visibility_score": 5.0
        },
        {
            "cpc": 0,
            "source": "ai_prediction",
            "keyword": "Google SEO",
            "difficulty": 50,
            "competition": 0.5,
            "is_hidden_gem": false,
            "search_volume": 0,
            "relevance_score": 0.6,
            "opportunity_score": 0,
            "ai_visibility_score": 5.0
        }
    ],
    "metadata": {
        "sources": {
            "ai_prediction": 30,
            "google_autocomplete": 28
        },
        "avg_search_volume": 0,
        "avg_opportunity_score": 1.4
    },
    "completed_at": "2026-01-15T11:27:59.005Z",
    "created_at": "2026-01-15T11:26:06.762Z",
    "filtered_keywords_count": 58
}